menglingtool_hive/__init__.py
menglingtool_hive/home.py
menglingtool_hive/queen_bee.py
menglingtool_hive/work_bee.py
menglingtool_hive-1.0.1.dist-info/METADATA
menglingtool_hive-1.0.1.dist-info/WHEEL
menglingtool_hive-1.0.1.dist-info/top_level.txt
menglingtool_hive-1.0.1.dist-info/RECORD
